vidtoolz_colored_textclip/__init__.py
vidtoolz_colored_textclip-0.0.2.dist-info/licenses/LICENSE
vidtoolz_colored_textclip-0.0.2.dist-info/METADATA
vidtoolz_colored_textclip-0.0.2.dist-info/WHEEL
vidtoolz_colored_textclip-0.0.2.dist-info/entry_points.txt
vidtoolz_colored_textclip-0.0.2.dist-info/top_level.txt
vidtoolz_colored_textclip-0.0.2.dist-info/RECORD
