Metadata-Version: 2.4
Name: vidtoolz-colored-textclip
Version: 0.0.2
Summary: Create a color clip with overlaid text
Author: Sukhbinder Singh
License: Apache-2.0
Project-URL: Homepage, https://github.com/sukhbinder/vidtoolz-colored-textclip
Project-URL: Changelog, https://github.com/sukhbinder/vidtoolz-colored-textclip/releases
Project-URL: Issues, https://github.com/sukhbinder/vidtoolz-colored-textclip/issues
Project-URL: CI, https://github.com/sukhbinder/vidtoolz-colored-textclip/actions
Classifier: License :: OSI Approved :: Apache Software License
License-File: LICENSE
Requires-Dist: vidtoolz
Requires-Dist: numpy
Provides-Extra: test
Requires-Dist: pytest; extra == "test"
Dynamic: license-file
